LICENSE-3RD-PARTY.txt
LICENSE.txt
MANIFEST.in
README.txt
setup.cfg
setup.py
test-requirements.txt
osensaplantiga/__init__.py
osensaplantiga/avrogeneration.py
osensaplantiga/constants.py
osensaplantiga/crc.py
osensaplantiga/custom_exceptions.py
osensaplantiga/minimalmodbusosensa.py
osensaplantiga/osensaplantiga.py
osensaplantiga/recordgeneration.py
osensaplantiga/test_avrogeneration.py
osensaplantiga/test_crc.py
osensaplantiga/test_osensaplantiga.py
osensaplantiga/test_recordgeneration.py
osensaplantiga/test_data/__init__.py
osensaplantiga/test_data/gen_test_data.py
osensaplantiga_dev.egg-info/PKG-INFO
osensaplantiga_dev.egg-info/SOURCES.txt
osensaplantiga_dev.egg-info/dependency_links.txt
osensaplantiga_dev.egg-info/requires.txt
osensaplantiga_dev.egg-info/top_level.txt