Metadata-Version: 1.2
Name: osensaplantiga-dev
Version: 0.1.15
Summary: OSENSA-Plantiga Python library
Home-page: UNKNOWN
Author: OSENSA Innovations
Author-email: cng@osensa.com
License: MIT
Platform: UNKNOWN
Requires-Python: >=3.6
